Workbook

Sheet Assumptions
A1: Delegate AI -- Antigravity-AI — Input Assumptions
A2: Generated: March 17, 2026
A4: Parameter | B4: Value | C4: Description
A5: Agents | B5: 18 | C5: Total specialist agents in V7 Router
A6: Cost per Agent ($/mo) | B6: 50 | C6: Monthly cost per agent
A7: Monthly Revenue (Base) | B7: 100000 | C7: Starting monthly revenue
A8: Growth Rate (MoM) | B8: 0.08 | C8: Month-over-month growth rate
A9: Fixed Costs ($/mo) | B9: 25000 | C9: Rent, infra, overhead
A10: Startup Investment | B10: 150000 | C10: Initial capital deployed
A11: Revenue per Agent | B11: =B7/B5 | C11: =B7/B5
A12: Total Annual Agent Cost | B12: =B5*B6*12 | C12: =B5*B6*12

Sheet Monthly P&L
A1: Month | B1: Volume Factor | C1: Revenue | D1: Agent Costs | E1: Fixed Costs | F1: Gross Profit | G1: Net Profit | H1: Margin % | I1: Cumulative Profit
A2: 1 | B2: =(1+Assumptions!B8)^(A2-1) | C2: =Assumptions!B7*B2 | D2: =Assumptions!B5*Assumptions!B6 | E2: =Assumptions!B9 | F2: =C2-D2 | G2: =F2-E2 | H2: =IF(C2>0,G2/C2,0) | I2: =G2-Assumptions!B10
A3: 2 | B3: =(1+Assumptions!B8)^(A3-1) | C3: =Assumptions!B7*B3 | D3: =Assumptions!B5*Assumptions!B6 | E3: =Assumptions!B9 | F3: =C3-D3 | G3: =F3-E3 | H3: =IF(C3>0,G3/C3,0) | I3: =I2+G3
A4: 3 | B4: =(1+Assumptions!B8)^(A4-1) | C4: =Assumptions!B7*B4 | D4: =Assumptions!B5*Assumptions!B6 | E4: =Assumptions!B9 | F4: =C4-D4 | G4: =F4-E4 | H4: =IF(C4>0,G4/C4,0) | I4: =I3+G4
A5: 4 | B5: =(1+Assumptions!B8)^(A5-1) | C5: =Assumptions!B7*B5 | D5: =Assumptions!B5*Assumptions!B6 | E5: =Assumptions!B9 | F5: =C5-D5 | G5: =F5-E5 | H5: =IF(C5>0,G5/C5,0) | I5: =I4+G5
A6: 5 | B6: =(1+Assumptions!B8)^(A6-1) | C6: =Assumptions!B7*B6 | D6: =Assumptions!B5*Assumptions!B6 | E6: =Assumptions!B9 | F6: =C6-D6 | G6: =F6-E6 | H6: =IF(C6>0,G6/C6,0) | I6: =I5+G6
A7: 6 | B7: =(1+Assumptions!B8)^(A7-1) | C7: =Assumptions!B7*B7 | D7: =Assumptions!B5*Assumptions!B6 | E7: =Assumptions!B9 | F7: =C7-D7 | G7: =F7-E7 | H7: =IF(C7>0,G7/C7,0) | I7: =I6+G7
A8: 7 | B8: =(1+Assumptions!B8)^(A8-1) | C8: =Assumptions!B7*B8 | D8: =Assumptions!B5*Assumptions!B6 | E8: =Assumptions!B9 | F8: =C8-D8 | G8: =F8-E8 | H8: =IF(C8>0,G8/C8,0) | I8: =I7+G8
A9: 8 | B9: =(1+Assumptions!B8)^(A9-1) | C9: =Assumptions!B7*B9 | D9: =Assumptions!B5*Assumptions!B6 | E9: =Assumptions!B9 | F9: =C9-D9 | G9: =F9-E9 | H9: =IF(C9>0,G9/C9,0) | I9: =I8+G9
A10: 9 | B10: =(1+Assumptions!B8)^(A10-1) | C10: =Assumptions!B7*B10 | D10: =Assumptions!B5*Assumptions!B6 | E10: =Assumptions!B9 | F10: =C10-D10 | G10: =F10-E10 | H10: =IF(C10>0,G10/C10,0) | I10: =I9+G10
A11: 10 | B11: =(1+Assumptions!B8)^(A11-1) | C11: =Assumptions!B7*B11 | D11: =Assumptions!B5*Assumptions!B6 | E11: =Assumptions!B9 | F11: =C11-D11 | G11: =F11-E11 | H11: =IF(C11>0,G11/C11,0) | I11: =I10+G11
A12: 11 | B12: =(1+Assumptions!B8)^(A12-1) | C12: =Assumptions!B7*B12 | D12: =Assumptions!B5*Assumptions!B6 | E12: =Assumptions!B9 | F12: =C12-D12 | G12: =F12-E12 | H12: =IF(C12>0,G12/C12,0) | I12: =I11+G12
A13: 12 | B13: =(1+Assumptions!B8)^(A13-1) | C13: =Assumptions!B7*B13 | D13: =Assumptions!B5*Assumptions!B6 | E13: =Assumptions!B9 | F13: =C13-D13 | G13: =F13-E13 | H13: =IF(C13>0,G13/C13,0) | I13: =I12+G13
A14: TOTAL | C14: =SUM(C2:C13) | D14: =SUM(D2:D13) | E14: =SUM(E2:E13) | F14: =SUM(F2:F13) | G14: =SUM(G2:G13) | H14: =IF(C14>0,G14/C14,0)

Sheet Cost Distribution
A1: Category | B1: Monthly Cost | C1: Annual Cost | D1: % of Total
A2: Agent Costs | B2: =Assumptions!B5*Assumptions!B6 | C2: =B2*12 | D2: =IF(B5>0,B2/B5,0)
A3: Fixed Costs | B3: =Assumptions!B9 | C3: =B3*12 | D3: =IF(B5>0,B3/B5,0)
A4: Investment (Amortized 12mo) | B4: =Assumptions!B10/12 | C4: =B4*12 | D4: =IF(B5>0,B4/B5,0)
A5: TOTAL | B5: =SUM(B2:B4) | C5: =SUM(C2:C4)

Sheet Sensitivity Analysis
A1: What-If: Cost Sensitivity Analysis
A3: Scenario | B3: Agent Cost | C3: Fixed Cost | D3: Annual Net Profit | E3: Margin %
A4: Base Case | B4: =Assumptions!B6*1.0 | C4: =Assumptions!B9*1.0 | D4: =(Assumptions!B7*12-Assumptions!B5*B4*12-C4*12) | E4: =IF(Assumptions!B7*12>0,D4/(Assumptions!B7*12),0)
A5: Costs +25% | B5: =Assumptions!B6*1.25 | C5: =Assumptions!B9*1.25 | D5: =(Assumptions!B7*12-Assumptions!B5*B5*12-C5*12) | E5: =IF(Assumptions!B7*12>0,D5/(Assumptions!B7*12),0)
A6: Costs +50% | B6: =Assumptions!B6*1.5 | C6: =Assumptions!B9*1.5 | D6: =(Assumptions!B7*12-Assumptions!B5*B6*12-C6*12) | E6: =IF(Assumptions!B7*12>0,D6/(Assumptions!B7*12),0)
A7: Costs Doubled | B7: =Assumptions!B6*2.0 | C7: =Assumptions!B9*2.0 | D7: =(Assumptions!B7*12-Assumptions!B5*B7*12-C7*12) | E7: =IF(Assumptions!B7*12>0,D7/(Assumptions!B7*12),0)
A8: Costs Tripled | B8: =Assumptions!B6*3.0 | C8: =Assumptions!B9*3.0 | D8: =(Assumptions!B7*12-Assumptions!B5*B8*12-C8*12) | E8: =IF(Assumptions!B7*12>0,D8/(Assumptions!B7*12),0)
A9: Revenue -20% | B9: =Assumptions!B6*1.0 | C9: =Assumptions!B9*1.0 | D9: =(Assumptions!B7*0.8*12-Assumptions!B5*Assumptions!B6*12-Assumptions!B9*12) | E9: =IF(Assumptions!B7*0.8*12>0,D9/(Assumptions!B7*0.8*12),0)

Sheet Agent Economics
A1: Agent | B1: Monthly Cost | C1: Decisions/Mo | D1: Cost/Decision | E1: ROI Contribution
A2: CEO | B2: =Assumptions!B6 | C2: 150 | D2: =IF(C2>0,B2/C2,0) | E2: =IF(B2>0,(Assumptions!B7/Assumptions!B5)/B2,0)
A3: CFO | B3: =Assumptions!B6 | C3: 170 | D3: =IF(C3>0,B3/C3,0) | E3: =IF(B3>0,(Assumptions!B7/Assumptions!B5)/B3,0)
A4: CTO | B4: =Assumptions!B6 | C4: 190 | D4: =IF(C4>0,B4/C4,0) | E4: =IF(B4>0,(Assumptions!B7/Assumptions!B5)/B4,0)
A5: CMO | B5: =Assumptions!B6 | C5: 210 | D5: =IF(C5>0,B5/C5,0) | E5: =IF(B5>0,(Assumptions!B7/Assumptions!B5)/B5,0)
A6: Deep Crawler | B6: =Assumptions!B6 | C6: 230 | D6: =IF(C6>0,B6/C6,0) | E6: =IF(B6>0,(Assumptions!B7/Assumptions!B5)/B6,0)
A7: The Critic | B7: =Assumptions!B6 | C7: 250 | D7: =IF(C7>0,B7/C7,0) | E7: =IF(B7>0,(Assumptions!B7/Assumptions!B5)/B7,0)
A8: The Librarian | B8: =Assumptions!B6 | C8: 270 | D8: =IF(C8>0,B8/C8,0) | E8: =IF(B8>0,(Assumptions!B7/Assumptions!B5)/B8,0)
A9: Compliance | B9: =Assumptions!B6 | C9: 290 | D9: =IF(C9>0,B9/C9,0) | E9: =IF(B9>0,(Assumptions!B7/Assumptions!B5)/B9,0)
A10: Data Architect | B10: =Assumptions!B6 | C10: 310 | D10: =IF(C10>0,B10/C10,0) | E10: =IF(B10>0,(Assumptions!B7/Assumptions!B5)/B10,0)
A11: Researcher | B11: =Assumptions!B6 | C11: 330 | D11: =IF(C11>0,B11/C11,0) | E11: =IF(B11>0,(Assumptions!B7/Assumptions!B5)/B11,0)
A12: Designer | B12: =Assumptions!B6 | C12: 350 | D12: =IF(C12>0,B12/C12,0) | E12: =IF(B12>0,(Assumptions!B7/Assumptions!B5)/B12,0)
A13: Presentations | B13: =Assumptions!B6 | C13: 370 | D13: =IF(C13>0,B13/C13,0) | E13: =IF(B13>0,(Assumptions!B7/Assumptions!B5)/B13,0)
A14: CX Strategist | B14: =Assumptions!B6 | C14: 390 | D14: =IF(C14>0,B14/C14,0) | E14: =IF(B14>0,(Assumptions!B7/Assumptions!B5)/B14,0)
A15: Aether | B15: =Assumptions!B6 | C15: 410 | D15: =IF(C15>0,B15/C15,0) | E15: =IF(B15>0,(Assumptions!B7/Assumptions!B5)/B15,0)
A16: Delegate AI | B16: =Assumptions!B6 | C16: 430 | D16: =IF(C16>0,B16/C16,0) | E16: =IF(B16>0,(Assumptions!B7/Assumptions!B5)/B16,0)
A17: EQ Engine | B17: =Assumptions!B6 | C17: 450 | D17: =IF(C17>0,B17/C17,0) | E17: =IF(B17>0,(Assumptions!B7/Assumptions!B5)/B17,0)
A18: GeoTalent Scout | B18: =Assumptions!B6 | C18: 470 | D18: =IF(C18>0,B18/C18,0) | E18: =IF(B18>0,(Assumptions!B7/Assumptions!B5)/B18,0)
A19: News Bureau | B19: =Assumptions!B6 | C19: 490 | D19: =IF(C19>0,B19/C19,0) | E19: =IF(B19>0,(Assumptions!B7/Assumptions!B5)/B19,0)
