Workbook

Sheet Assumptions
A1: Parameter | B1: Value | C1: Description
A2: unit_cost_product_a | B2: 0
A3: price_product_a | B3: 0
A4: unit_cost_product_b | B4: 0
A5: price_product_b | B5: 0
A6: fixed_costs_monthly | B6: 0
A7: startup_investment | B7: 0
A8: sales_growth_rate | B8: 0
A9: initial_sales_volume | B9: 0

Sheet P&L Year 1
A1: Month | B1: Volume | C1: Revenue | D1: COGS | E1: Gross Profit | F1: Fixed Costs | G1: Net Profit
A2: 1 | B2: =Assumptions!B9*(1+Assumptions!B8)^(A2-1) | C2: =(B2*0.5*Assumptions!B3)+(B2*0.5*Assumptions!B5) | D2: =(B2*0.5*Assumptions!B2)+(B2*0.5*Assumptions!B4) | E2: =C2-D2 | F2: =Assumptions!B6 | G2: =E2-F2
A3: 2 | B3: =Assumptions!B9*(1+Assumptions!B8)^(A3-1) | C3: =(B3*0.5*Assumptions!B3)+(B3*0.5*Assumptions!B5) | D3: =(B3*0.5*Assumptions!B2)+(B3*0.5*Assumptions!B4) | E3: =C3-D3 | F3: =Assumptions!B6 | G3: =E3-F3
A4: 3 | B4: =Assumptions!B9*(1+Assumptions!B8)^(A4-1) | C4: =(B4*0.5*Assumptions!B3)+(B4*0.5*Assumptions!B5) | D4: =(B4*0.5*Assumptions!B2)+(B4*0.5*Assumptions!B4) | E4: =C4-D4 | F4: =Assumptions!B6 | G4: =E4-F4
A5: 4 | B5: =Assumptions!B9*(1+Assumptions!B8)^(A5-1) | C5: =(B5*0.5*Assumptions!B3)+(B5*0.5*Assumptions!B5) | D5: =(B5*0.5*Assumptions!B2)+(B5*0.5*Assumptions!B4) | E5: =C5-D5 | F5: =Assumptions!B6 | G5: =E5-F5
A6: 5 | B6: =Assumptions!B9*(1+Assumptions!B8)^(A6-1) | C6: =(B6*0.5*Assumptions!B3)+(B6*0.5*Assumptions!B5) | D6: =(B6*0.5*Assumptions!B2)+(B6*0.5*Assumptions!B4) | E6: =C6-D6 | F6: =Assumptions!B6 | G6: =E6-F6
A7: 6 | B7: =Assumptions!B9*(1+Assumptions!B8)^(A7-1) | C7: =(B7*0.5*Assumptions!B3)+(B7*0.5*Assumptions!B5) | D7: =(B7*0.5*Assumptions!B2)+(B7*0.5*Assumptions!B4) | E7: =C7-D7 | F7: =Assumptions!B6 | G7: =E7-F7
A8: 7 | B8: =Assumptions!B9*(1+Assumptions!B8)^(A8-1) | C8: =(B8*0.5*Assumptions!B3)+(B8*0.5*Assumptions!B5) | D8: =(B8*0.5*Assumptions!B2)+(B8*0.5*Assumptions!B4) | E8: =C8-D8 | F8: =Assumptions!B6 | G8: =E8-F8
A9: 8 | B9: =Assumptions!B9*(1+Assumptions!B8)^(A9-1) | C9: =(B9*0.5*Assumptions!B3)+(B9*0.5*Assumptions!B5) | D9: =(B9*0.5*Assumptions!B2)+(B9*0.5*Assumptions!B4) | E9: =C9-D9 | F9: =Assumptions!B6 | G9: =E9-F9
A10: 9 | B10: =Assumptions!B9*(1+Assumptions!B8)^(A10-1) | C10: =(B10*0.5*Assumptions!B3)+(B10*0.5*Assumptions!B5) | D10: =(B10*0.5*Assumptions!B2)+(B10*0.5*Assumptions!B4) | E10: =C10-D10 | F10: =Assumptions!B6 | G10: =E10-F10
A11: 10 | B11: =Assumptions!B9*(1+Assumptions!B8)^(A11-1) | C11: =(B11*0.5*Assumptions!B3)+(B11*0.5*Assumptions!B5) | D11: =(B11*0.5*Assumptions!B2)+(B11*0.5*Assumptions!B4) | E11: =C11-D11 | F11: =Assumptions!B6 | G11: =E11-F11
A12: 11 | B12: =Assumptions!B9*(1+Assumptions!B8)^(A12-1) | C12: =(B12*0.5*Assumptions!B3)+(B12*0.5*Assumptions!B5) | D12: =(B12*0.5*Assumptions!B2)+(B12*0.5*Assumptions!B4) | E12: =C12-D12 | F12: =Assumptions!B6 | G12: =E12-F12
A13: 12 | B13: =Assumptions!B9*(1+Assumptions!B8)^(A13-1) | C13: =(B13*0.5*Assumptions!B3)+(B13*0.5*Assumptions!B5) | D13: =(B13*0.5*Assumptions!B2)+(B13*0.5*Assumptions!B4) | E13: =C13-D13 | F13: =Assumptions!B6 | G13: =E13-F13
A14: TOTAL | B14: =SUM(B2:B13) | C14: =SUM(C2:C13) | D14: =SUM(D2:D13) | E14: =SUM(E2:E13) | F14: =SUM(F2:F13) | G14: =SUM(G2:G13)
